{ "hypothesis": "Class-held-out AUC > 0.85 distinguishing GRH-true vs GRH-false", "training_classes": [ "F1", "F4", "F9" ], "test_classes": [ "F2", "F5p", "F5m", "F6", "F7", "F10", "F11", "F12" ], "features": [ "log_abs_S1_norm", "log_abs_S2_norm", "log_abs_S3_norm", "log_abs_S4_norm", "log_abs_S5_norm", "log_abs_S6_norm" ], "train_GRH_counts": { "true": 400, "false": 200 }, "test_GRH_counts": { "true": 1000, "false": 600 }, "train_AUC": 0.980875, "test_AUC": 0.9143333333333334, "test_AUC_bootstrap_mean": 0.9140805832247804, "test_AUC_95CI": [ 0.9000540485090532, 0.9273177813397854 ], "strict_test_AUC_F12_only_violator": 0.827735, "strict_AUC_95CI": [ 0.8059629023295011, 0.8486749752680762 ], "confusion_matrix": [ [ 849, 151 ], [ 182, 418 ] ], "confusion_matrix_labels": [ "true_GRH_true", "true_GRH_false", "pred_GRH_true", "pred_GRH_false" ], "per_class_F12_recall_at_0.5": 0.27, "note": "Hypothesis AUC>0.85 confirmed for full 8-class held-out test set (CI excludes 0.85 from below). However, the truly novel violator F12 has only 27% recall at threshold 0.5 and the strict-F12-only AUC of 0.83 has 95% CI [0.81, 0.85] which contains the threshold. The strong overall AUC is partly driven by F5\u00b1 resembling F4 (DH family) which is in the training set."
}